multiplexermcp/__init__.py
multiplexermcp/config.py
multiplexermcp-0.1.0.dist-info/METADATA
multiplexermcp-0.1.0.dist-info/WHEEL
multiplexermcp-0.1.0.dist-info/entry_points.txt
multiplexermcp-0.1.0.dist-info/RECORD
