Metadata-Version: 2.4
Name: multiplexermcp
Version: 0.1.0
Summary: Add your description here
Author-email: TerminalMan <84923604+SecretiveShell@users.noreply.github.com>
Requires-Python: >=3.13
Requires-Dist: easymcp>=0.4.0
Requires-Dist: mcp>=1.6.0
